LICENSE
MANIFEST.in
README.md
package.json
setup.py
checkbox_tree/CheckboxTree.py
checkbox_tree/__init__.py
checkbox_tree/_imports_.py
checkbox_tree/checkbox_tree.min.js
checkbox_tree/checkbox_tree.min.js.map
checkbox_tree/metadata.json
checkbox_tree/package-info.json
checkbox_tree.egg-info/PKG-INFO
checkbox_tree.egg-info/SOURCES.txt
checkbox_tree.egg-info/dependency_links.txt
checkbox_tree.egg-info/top_level.txt