Metadata-Version: 2.1
Name: checkbox-tree
Version: 0.0.1
Summary: Dash Wrapper for React Checkbox Tree
Author: Maxine Lai <ms.l@hotmail.com>
License: MIT
Classifier: Framework :: Dash
License-File: LICENSE
